tori/__init__.py
tori/application.py
tori/centre.py
tori/common.py
tori/controller.py
tori/exception.py
tori/graph.py
tori/handler.py
tori/navigation.py
tori/cli/__init__.py
tori/cli/command.py
tori/cli/console.py
tori/cli/exception.py
tori/data/__init__.py
tori/data/base.py
tori/data/compressor.py
tori/data/exception.py
tori/data/serializer.py
tori/decorator/__init__.py
tori/decorator/common.py
tori/decorator/controller.py
tori/session/__init__.py
tori/session/controller.py
tori/session/generator.py
tori/session/entity/__init__.py
tori/session/entity/base.py
tori/session/entity/database.py
tori/session/entity/document.py
tori/session/repository/__init__.py
tori/session/repository/base.py
tori/session/repository/collection.py
tori/session/repository/database.py
tori/session/repository/file.py
tori/session/repository/memory.py
tori/session/repository/xredis.py
tori/socket/__init__.py
tori/socket/rpc.py
tori/socket/websocket.py
tori/template/__init__.py
tori/template/renderer.py
tori/template/repository.py
tori/template/service.py
tori-3.1.2.data/scripts/nest
tori-3.1.2.dist-info/DESCRIPTION.rst
tori-3.1.2.dist-info/METADATA
tori-3.1.2.dist-info/metadata.json
tori-3.1.2.dist-info/RECORD
tori-3.1.2.dist-info/top_level.txt
tori-3.1.2.dist-info/WHEEL
