Metadata-Version: 2.0
Name: tori
Version: 3.1.2
Summary: A collection of libraries and a micro web framework based on Tornado framework
Home-page: http://shiroyuki.com/projects/tori.html
Author: Juti Noppornpitak
Author-email: juti_n@yahoo.co.jp
License: MIT
Platform: UNKNOWN
Classifier: Development Status :: 5 - Production/Stable
Classifier: Environment :: Web Environment
Classifier: Intended Audience :: Developers
Classifier: License :: OSI Approved :: MIT License
Classifier: Operating System :: OS Independent
Classifier: Programming Language :: Python
Classifier: Programming Language :: Python :: 2.7
Classifier: Programming Language :: Python :: 3
Classifier: Topic :: Internet :: WWW/HTTP :: Dynamic Content
Classifier: Topic :: Software Development :: Libraries
Requires-Dist: passerine
Requires-Dist: imagination
Requires-Dist: kotoba
Requires-Dist: tornado
Requires-Dist: jinja2
